{
  "collapse-filter": false,
  "search": "path:calculus  ",
  "showTags": false,
  "showAttachments": false,
  "hideUnresolved": false,
  "showOrphans": true,
  "collapse-color-groups": false,
  "colorGroups": [
    {
      "query": "tag:#定义  ",
      "color": {
        "a": 1,
        "rgb": 14048348
      }
    },
    {
      "query": "tag:#定理  ",
      "color": {
        "a": 1,
        "rgb": 14069084
      }
    }
  ],
  "collapse-display": false,
  "showArrow": true,
  "textFadeMultiplier": 0,
  "nodeSizeMultiplier": 1.69879446640316,
  "lineSizeMultiplier": 2.46522491349481,
  "collapse-forces": false,
  "centerStrength": 0.518713248970312,
  "repelStrength": 10,
  "linkStrength": 1,
  "linkDistance": 250,
  "scale": 1.2101129662065329,
  "close": false
}